{
    "settings": {
        "autoAdvance": true,
        "interval": 5000,
        "pauseOnHover": true,
        "transitionMs": 900,
        "showArrows": true,
        "showDots": true,
        "initialSlide": 0
    },
    "slides": [
        {
            "image": "hero_00.jpg",
            "alt": "QX desk system in a modern open-space office with people working",
            "description": "Open-space layout with collaborative desks."
        },
        {
            "image": "hero_01.jpg",
            "alt": "QX desk with ergonomic chairs in a bright office interior",
            "description": "Focus zone optimized for ergonomic work."
        },
        {
            "image": "hero_02.jpg",
            "alt": "QX modular desks arranged in a contemporary workspace",
            "description": "Modular arrangement for team scalability."
        },
        {
            "image": "hero_03.jpg",
            "alt": "QX workstation detail in modern office environment",
            "description": "Product detail highlighting finishes and precision."
        }
    ],
    "descriptionStyle": {
        "enabled": true,
        "position": "bottom-left",
        "offsetPx": 34,
        "textColor": "#F4ECE4",
        "backgroundColor": "transparent",
        "backdropBlurPx": 0,
        "paddingX": 0,
        "paddingY": 0,
        "borderRadiusPx": 0,
        "fontSizePx": 42,
        "fontWeight": 200,
        "letterSpacingEm": 0.02,
        "maxWidth": "720px",
        "textAlign": "left",
        "uppercase": false
    }
}